grace/__init__.py
grace/application.py
grace/bot.py
grace/cli.py
grace/config.py
grace/database.py
grace/exceptions.py
grace/generator.py
grace/importer.py
grace/model.py
grace/generators/__init__.py
grace/generators/cog_generator.py
grace/generators/migration_generator.py
grace/generators/model_generator.py
grace/generators/project_generator.py
grace/generators/templates/cog/{{ cog_name | to_snake }}_cog.py
grace/generators/templates/model/{{ model_name | to_snake }}.py
grace/generators/templates/project/cookiecutter.json
grace/generators/templates/project/hooks/post_gen_project.py
grace/generators/templates/project/{{ cookiecutter.__project_slug }}/.env
grace/generators/templates/project/{{ cookiecutter.__project_slug }}/README.md
grace/generators/templates/project/{{ cookiecutter.__project_slug }}/alembic.ini
grace/generators/templates/project/{{ cookiecutter.__project_slug }}/bot/__init__.py
grace/generators/templates/project/{{ cookiecutter.__project_slug }}/bot/{{ cookiecutter.__project_slug }}.py
grace/generators/templates/project/{{ cookiecutter.__project_slug }}/bot/extensions/__init__.py
grace/generators/templates/project/{{ cookiecutter.__project_slug }}/bot/helpers/__init__.py
grace/generators/templates/project/{{ cookiecutter.__project_slug }}/bot/models/__init__.py
grace/generators/templates/project/{{ cookiecutter.__project_slug }}/config/__init__.py
grace/generators/templates/project/{{ cookiecutter.__project_slug }}/config/database.cfg
grace/generators/templates/project/{{ cookiecutter.__project_slug }}/config/environment.cfg
grace/generators/templates/project/{{ cookiecutter.__project_slug }}/config/settings.cfg
grace/generators/templates/project/{{ cookiecutter.__project_slug }}/db/__init__.py
grace/generators/templates/project/{{ cookiecutter.__project_slug }}/db/seed.py
grace/generators/templates/project/{{ cookiecutter.__project_slug }}/db/alembic/env.py
grace_framework-1.4.2a0.dist-info/METADATA
grace_framework-1.4.2a0.dist-info/WHEEL
grace_framework-1.4.2a0.dist-info/entry_points.txt
grace_framework-1.4.2a0.dist-info/top_level.txt
grace_framework-1.4.2a0.dist-info/RECORD
