Metadata-Version: 2.4
Name: grace-framework
Version: 1.4.2a0
Summary: Extensible Discord bot framework based on Discord.py
Author: Code Society Lab
Author-email: Simon Roy <simon.roy1211@gmail.com>
License:                     GNU GENERAL PUBLIC LICENSE
Project-URL: Homepage, https://codesociety.xyz
Project-URL: Source, https://github.com/Code-Society-Lab/grace-framework
Requires-Python: >=3.10
Requires-Dist: discord>2.0
Requires-Dist: logger
Requires-Dist: coloredlogs
Requires-Dist: python-dotenv
Requires-Dist: configparser
Requires-Dist: click
Requires-Dist: sqlalchemy
Requires-Dist: sqlalchemy-utils
Requires-Dist: alembic==1.8.1
Requires-Dist: cookiecutter
Requires-Dist: jinja2-strcase
Requires-Dist: inflect
Requires-Dist: mypy
Requires-Dist: pytest
Requires-Dist: flake8
Requires-Dist: pytest-mock
Requires-Dist: inflect
Requires-Dist: coverage
